tests/__init__.py
tests/test.py
tf2crf/__init__.py
tf2crf/crf.py
tf2crf/model_wrapper.py
tf2crf/other_losses.py
tf2crf-0.1.33.dist-info/LICENSE
tf2crf-0.1.33.dist-info/METADATA
tf2crf-0.1.33.dist-info/WHEEL
tf2crf-0.1.33.dist-info/top_level.txt
tf2crf-0.1.33.dist-info/RECORD
