Metadata-Version: 2.1
Name: tf2crf
Version: 0.1.33
Summary: a crf layer for tensorflow 2 keras
Home-page: https://github.com/xuxingya/tf2crf
Author: xingya.xu
Author-email: xingya.xu@gmail.com
License: MIT License
Platform: UNKNOWN
Requires-Dist: tensorflow (>=2.1.0)
Requires-Dist: tensorflow-addons (>=0.8.2)
